CHANGES.rst
LICENSE
MANIFEST.in
README.rst
setup.py
VKAppAuth.egg-info/PKG-INFO
VKAppAuth.egg-info/SOURCES.txt
VKAppAuth.egg-info/dependency_links.txt
VKAppAuth.egg-info/requires.txt
VKAppAuth.egg-info/top_level.txt
bin/vkappauth.py
vkappauth/__init__.py
vkappauth/vk_app_auth.py
vkappauth/vk_form_parser.py