Metadata-Version: 1.1
Name: VKAppAuth
Version: 0.0.1
Summary: Python package for authorize a standalone VK/Vkontakte application and getaccess_token for vkontakte api.
Home-page: https://github.com/speechkey/vkappauth
Author: Artem Grebenkin
Author-email: artem.grebenkin@gmail.com
License: MIT
Download-URL: https://github.com/speechkey/VKAppAuth/tarball/0.0.1
Keywords: vkontakte vk api access_token oauth oauth2
Platform: UNKNOWN
Classifier: Development Status :: 5 - Production/Stable
Classifier: Intended Audience :: Developers
Classifier: License :: OSI Approved :: MIT License
Classifier: Operating System :: OS Independent
Classifier: Programming Language :: Python
Classifier: Programming Language :: Python :: 2.6
Classifier: Programming Language :: Python :: 2.7
Classifier: Topic :: Internet :: WWW/HTTP
